enot_latency_server/__init__.py
enot_latency_server/client.py
enot_latency_server/server.py
enot_latency_server-1.2.1.dist-info/LICENSE
enot_latency_server-1.2.1.dist-info/METADATA
enot_latency_server-1.2.1.dist-info/WHEEL
enot_latency_server-1.2.1.dist-info/top_level.txt
enot_latency_server-1.2.1.dist-info/RECORD
