Metadata-Version: 2.1
Name: enot-latency-server
Version: 1.2.1
Summary: Latency measurement server/client for ENOT Framework
Author-email: ENOT LLC <enot@enot.ai>
License: Apache License
Project-URL: homepage, https://enot.ai
Project-URL: documentation, https://enot-autodl.rtd.enot.ai/en/stable
Keywords: ENOT,latency,measure
Classifier: Development Status :: 5 - Production/Stable
Classifier: License :: OSI Approved :: Apache Software License
Classifier: Programming Language :: Python
Classifier: Programming Language :: Python :: 3.6
Classifier: Programming Language :: Python :: 3.7
Classifier: Programming Language :: Python :: 3.8
Classifier: Programming Language :: Python :: 3.9
Classifier: Programming Language :: Python :: 3 :: Only
Requires-Python: >=3.6
License-File: LICENSE
Requires-Dist: requests
Requires-Dist: aiohttp
